lib_template/__init__.py
lib_template/hello_world.py
tests/__init__.py
tests/test_hello_world.py
lib_template-0.0.1.dist-info/METADATA
lib_template-0.0.1.dist-info/WHEEL
lib_template-0.0.1.dist-info/top_level.txt
lib_template-0.0.1.dist-info/RECORD
